resume_gen/__init__.py
resume_gen/core/__init__.py
resume_gen/core/person.py
resume_gen/core/resume.py
resume_gen-0.0.2.dist-info/METADATA
resume_gen-0.0.2.dist-info/WHEEL
resume_gen-0.0.2.dist-info/top_level.txt
resume_gen-0.0.2.dist-info/RECORD
