Metadata-Version: 2.1
Name: resume-gen
Version: 0.0.2
Summary: Generate resumes from template(s) using a person's data.
Home-page: https://github.com/Brok-Bucholtz/resume-generator
Author: Brok Bucholtz
Author-email: UNKNOWN
License: UNKNOWN
Platform: UNKNOWN
